ndview/__init__.py
ndview/core.py
ndview-0.0.6.dist-info/LICENSE.md
ndview-0.0.6.dist-info/METADATA
ndview-0.0.6.dist-info/WHEEL
ndview-0.0.6.dist-info/top_level.txt
ndview-0.0.6.dist-info/RECORD
