Metadata-Version: 2.1
Name: ndview
Version: 0.0.6
Summary: Multidimensional array viewer widget for jupyter
Home-page: https://github.com/danionella/ndview
Author: jlab.berlin
License: mit
Requires-Python: >=3.5
License-File: LICENSE.md
Requires-Dist: matplotlib
Requires-Dist: ipywidgets
Requires-Dist: ipympl
Requires-Dist: numpy
